pythmc/__init__.py
pythmc/Chat/chat_parser.py
pythmc/Chat/message.py
pythmc/Chat/minecraft.py
pythmc/Interactions/minecraft.py
pythmc/assets/exceptions.py
pythmc/assets/essentials/interactor.py
pythmc/assets/essentials/keybinds.py
PythMC-1.2.2.dist-info/LICENSE
PythMC-1.2.2.dist-info/METADATA
PythMC-1.2.2.dist-info/WHEEL
PythMC-1.2.2.dist-info/top_level.txt
PythMC-1.2.2.dist-info/RECORD
