Metadata-Version: 2.1
Name: PythMC
Version: 1.2.2
Summary: A Library used to interact with the Minecraft Environment in Python.
Home-page: https://github.com/MrKelpy/PythMC
Author: Alexandre Silva // MrKelpy
Author-email: alexandresilva.coding@gmail.com
License: UNKNOWN
Platform: UNKNOWN
Classifier: Programming Language :: Python :: 3
Classifier: License :: OSI Approved :: GNU General Public License v3 (GPLv3)
Classifier: Operating System :: OS Independent
Requires-Python: >=3.7
License-File: LICENSE
Requires-Dist: mouse
Requires-Dist: keyboard
